finance_analyzer/__init__.py
finance_analyzer/analyze.py
finance_analyzer/cli.py
my_finance_analyzer228-0.1.0.dist-info/METADATA
my_finance_analyzer228-0.1.0.dist-info/WHEEL
my_finance_analyzer228-0.1.0.dist-info/entry_points.txt
my_finance_analyzer228-0.1.0.dist-info/top_level.txt
my_finance_analyzer228-0.1.0.dist-info/RECORD
