Metadata-Version: 2.1
Name: my-finance-analyzer228
Version: 0.1.0
Summary: A package to analyze financial transactions and generate a report
Author-email: Grigory <grig.perev@gmail.com>
License: MIT
Requires-Python: >=3.7
Requires-Dist: pandas
